kk.py
bso/__init__.py
bso/jj.py
zzjjkk-1.2.3.dist-info/LICENSE
zzjjkk-1.2.3.dist-info/METADATA
zzjjkk-1.2.3.dist-info/WHEEL
zzjjkk-1.2.3.dist-info/top_level.txt
zzjjkk-1.2.3.dist-info/RECORD
