Metadata-Version: 2.1
Name: zzjjkk
Version: 1.2.3
Summary: this is niubi file
Home-page: https://giehub.com
Author: lili
Author-email: lili@anytec.com
License: MIT
Platform: UNKNOWN
